README.md
setup.cfg
setup.py
prophet_tools/__init__.py
prophet_tools/auto_import.py
prophet_tools/file_convertors.py
prophet_tools/file_convertors_v2.py
prophet_tools/file_info.py
prophet_tools/how_to_import.py
prophet_tools/lists.py
prophet_tools/my_functions.py
prophet_tools/parsing.py
prophet_tools/shortcuts.py
prophet_tools/terminal.py
prophet_tools.egg-info/PKG-INFO
prophet_tools.egg-info/SOURCES.txt
prophet_tools.egg-info/dependency_links.txt
prophet_tools.egg-info/not-zip-safe
prophet_tools.egg-info/requires.txt
prophet_tools.egg-info/top_level.txt