Metadata-Version: 2.1
Name: prophet_tools
Version: 25.3
Summary: ProPHet personal tools
Author-email: prophet.incorporated@gmail.com
Requires-Dist: xlsxwriter==3.2.0
Requires-Dist: pillow==10.1.0
Requires-Dist: pillow-avif-plugin==1.4.3
Requires-Dist: comtypes==1.4.7
Requires-Dist: pymediainfo==6.1.0
